{
  "country": "finland",
  "source": {
    "api": "https://eperusteet.opintopolku.fi/eperusteet-service/api/external/peruste/419550/perusopetus/oppiaineet/600170",
    "curriculum": "POPS 2014",
    "license": "Open Government Data (Finland)",
    "lastSynced": "2026-03-03T16:02:25Z",
    "aiEnriched": [
      "description.en",
      "interdisciplinaryThemes",
      "basicSkills"
    ]
  },
  "subject": {
    "code": "VK",
    "name": {
      "local": "Englanti, A-oppimäärä",
      "en": "Foreign Languages (English)"
    },
    "description": {
      "local": "Kieli on oppimisen ja ajattelun edellytys. Kieli on mukana kaikessa koulun toiminnassa, ja jokainen opettaja on kielen opettaja. Kielten opiskelu edistää ajattelutaitojen kehittymistä. Se antaa aineksia monikielisen ja -kulttuurisen identiteetin muodostumiselle ja arvostamiselle. Sanavaraston ja rakenteiden karttuessa myös vuorovaikutus- ja tiedonhankintataidot kehittyvät. Kielten opiskelussa on runsaasti sijaa ilolle, leikillisyydelle ja luovuudelle.\n\nKieltenopetus on osa kielikasvatusta ja johdatusta kielitietoisuuteen. Oppilaissa herätetään kiinnostus kouluyhteisön ja ympäröivän maailman kielelliseen ja kulttuuriseen moninaisuuteen ja heitä rohkaistaan viestimään autenttisissa ympäristöissä. Koulussa ohjataan arvostamaan eri kieliä, niiden puhujia ja erilaisia kulttuureita. Sukupuolten tasa-arvoa kielivalinnoissa ja kielten opiskelussa vahvistetaan erilaisia oppilaita kiinnostavalla kielivalintatiedotuksella, rohkaisemalla oppilaita tekemään aidosti itseään kiinnostavia valintoja sukupuolesta riippumatta, käsittelemällä opetuksessa monipuolisesti erilaisia aiheita sekä käyttämällä vaihtelevia ja toiminnallisia työtapoja.\n\nKielten opiskelu valmistaa oppilaita suunnitelmalliseen ja luovaan työskentelyyn erilaisissa kokoonpanoissa. Oppilaille ja oppilasryhmille luodaan mahdollisuuksia verkostoitumiseen ja yhteydenpitoon ihmisten kanssa myös eri puolilla maailmaa. Tieto- ja viestintäteknologia tarjoaa yhden luontevan mahdollisuuden toteuttaa kieltenopetusta autenttisista tilanteista ja oppilaiden viestintätarpeista lähtien. Opetus antaa myös valmiuksia osallisuuteen ja aktiiviseen vaikuttamiseen kansainvälisessä maailmassa.\n\nOpetus vahvistaa oppilaiden luottamusta omiin kykyihinsä oppia kieliä ja käyttää niitä rohkeasti. Oppilaille annetaan mahdollisuus edetä yksilöllisesti ja saada tarpeen mukaan tukea oppimiselleen. Opetus järjestetään niin, että myös muita nopeammin etenevät tai kieltä entuudestaan osaavat voivat edistyä.\n\nKielten opetuksessa kehitetään monilukutaitoa ja käsitellään erilaisia tekstejä. Lasten ja nuorten erilaiset kiinnostuksen kohteet otetaan huomioon tekstien valinnassa. Opetuksessa luodaan siltoja myös eri kielten välille sekä oppilaiden vapaa-ajan kielenkäyttöön. Oppilaita ohjataan hakemaan osaamillaan kielillä tietoa.",
      "en": "Language is a prerequisite for learning and thinking. Language is present in all school activities, and every teacher is a language teacher. The study of languages promotes the development of thinking skills. It provides material for the formation and appreciation of a multilingual and multicultural identity. As vocabulary and structures accumulate, interaction and information-seeking skills also develop. There is ample room for joy, playfulness and creativity in language studies.\n\nLanguage teaching is part of language education and an introduction to language awareness. Interest in the linguistic and cultural diversity of the school community and the surrounding world is awakened in pupils, and they are encouraged to communicate in authentic environments. At school, pupils are guided to value different languages, their speakers and various cultures. Gender equality in language choices and language studies is strengthened through language choice information that appeals to diverse pupils, by encouraging pupils to make choices that genuinely interest them regardless of gender, by covering a wide range of topics in teaching, and by using varied and functional working methods.\n\nLanguage studies prepare pupils for systematic and creative work in various groupings. Opportunities are created for pupils and pupil groups to network and communicate with people around the world. Information and communication technology offers one natural opportunity to implement language teaching based on authentic situations and pupils' communication needs. Teaching also provides the readiness for participation and active influence in an international world.\n\nTeaching strengthens pupils' confidence in their own ability to learn languages and to use them boldly. Pupils are given the opportunity to progress individually and to receive support for their learning as needed. Teaching is organised so that those who progress faster than others or already know the language can also advance.\n\nMultiliteracy is developed in language teaching, and different types of texts are addressed. The diverse interests of children and young people are taken into account in the selection of texts. Teaching also builds bridges between different languages and pupils' use of language in their free time. Pupils are guided to seek information in the languages they know."
    },
    "coreElements": [
      {
        "code": "S1",
        "name": {
          "local": "S1 Kasvu kulttuuriseen moninaisuuteen ja kielitietoisuuteen",
          "en": "S1 Growing into Cultural Diversity and Language Awareness"
        },
        "description": {
          "local": "Rakennetaan ymmärrystä maailman moni- ja rinnakkaiskielisyydestä sekä kielellisistä oikeuksista. Tutkitaan englannin kielen kehittymistä globaaliksi lingua francaksi. Otetaan selkoa joidenkin sellaisten maiden kulttuureista ja elämänmuodoista, joissa englanti on keskeisin yhteiskunnassa käytetty kieli. Käytetään sellaisia kielitiedon käsitteitä, jotka auttavat oppilaita englannin kielen opiskelussa sekä kielten välisessä vertailussa. Hankitaan tietoa joistakin englannin kielen varianteista.",
          "en": "An understanding of the multilingual and parallel-language nature of the world and of linguistic rights is built. The development of English as a global lingua franca is investigated. The cultures and ways of life of some countries where English is the primary language used in society are explored. Linguistic concepts that help pupils in the study of English and in comparing languages are used. Information about some varieties of English is acquired."
        }
      },
      {
        "code": "S2",
        "name": {
          "local": "S2 Kielenopiskelutaidot",
          "en": "S2 Language Learning Skills"
        },
        "description": {
          "local": "Vahvistetaan edelleen kieltenopiskelutaitoja. Harjoitellaan oppimateriaalin monipuolista käyttöä, sanastojen käyttöä, kokonaisuuksien hahmottamista, ryhmittelyä, tiedon hakemista ja tiedon luotettavuuden arviointia.",
          "en": "Language learning skills are further strengthened. The versatile use of learning materials, the use of dictionaries, perceiving overall structures, categorisation, information retrieval, and evaluating the reliability of information are practised."
        }
      },
      {
        "code": "S3",
        "name": {
          "local": "S3 Kehittyvä kielitaito, taito toimia vuorovaikutuksessa, taito tulkita tekstejä, taito tuottaa tekstejä",
          "en": "S3 Developing Language Proficiency: Interaction Skills, Text Interpretation Skills, Text Production Skills"
        },
        "description": {
          "local": "Sisältöjä yhdessä valittaessa näkökulmana on nuoren toiminta englannin kielellä eri yhteisöissä, ajankohtaisuus, oppilaiden kiinnostuksen kohteet, suuntautuminen toisen asteen opintoihin sekä tutustuminen nuorten työelämässä ja opiskelussa tarvittavaan kielitaitoon sekä oppilaiden osallisuus ja toimijuus paikallisesti ja globaalisti. Otetaan huomioon englannin kielen levinneisyys ja asema globaalin kommunikaation kielenä. Sanastoa ja rakenteita opetellaan monenlaisista teksteistä, kuten kertovista, kuvaavista tai vaikuttavista teksteistä. Havainnoidaan ja harjoitellaan runsaasti erilaisia vuorovaikutustilanteita eri viestintäkanavia hyödyntäen.",
          "en": "When selecting content collaboratively, the perspective is the young person's use of English in different communities, topicality, pupils' interests, orientation towards upper secondary studies, and familiarisation with the language skills needed by young people in working life and studies, as well as pupils' participation and agency locally and globally. The spread and status of English as a language of global communication are taken into account. Vocabulary and structures are studied from various types of texts, such as narrative, descriptive, or persuasive texts. Various interaction situations are extensively observed and practised using different communication channels."
        }
      }
    ],
    "interdisciplinaryThemes": [
      {
        "code": "TT1",
        "name": {
          "local": "Terveys ja elämänhallinta",
          "en": "Health and life skills"
        },
        "description": {
          "local": "Vieraiden kielten opetuksessa tuetaan oppilaiden itseluottamusta ja myönteistä suhtautumista omaan oppimiseen, mikä vahvistaa heidän psyykkistä hyvinvointiaan. Oppilaat oppivat viestimään terveyteen ja hyvinvointiin liittyvistä aiheista kohdekielellä. Kielitaito antaa valmiuksia hakea terveyteen liittyvää tietoa kansainvälisistä lähteistä ja toimia erilaisissa arkielämän tilanteissa.",
          "en": "In foreign language teaching, pupils' self-confidence and positive attitude towards their own learning are supported, which strengthens their psychological well-being. Pupils learn to communicate about health and well-being topics in the target language. Language skills provide the capacity to seek health-related information from international sources and to function in various everyday situations."
        }
      },
      {
        "code": "TT2",
        "name": {
          "local": "Demokratia ja kansalaisuus",
          "en": "Democracy and citizenship"
        },
        "description": {
          "local": "Vieraiden kielten opiskelu kehittää kulttuurienvälistä toimintakykyä ja valmiuksia osallistua aktiivisesti kansainväliseen vuorovaikutukseen. Oppilaat oppivat kohtaamaan ihmisiä ilman arvottavia ennakko-oletuksia ja arvostamaan kielellistä moninaisuutta. Kielitaito mahdollistaa osallisuuden ja vaikuttamisen myös kansainvälisissä yhteyksissä.",
          "en": "The study of foreign languages develops intercultural competence and the readiness to participate actively in international interaction. Pupils learn to encounter people without prejudicial assumptions and to value linguistic diversity. Language skills enable participation and influence also in international contexts."
        }
      },
      {
        "code": "TT3",
        "name": {
          "local": "Kestävä kehitys",
          "en": "Sustainability"
        },
        "description": {
          "local": "Vieraiden kielten opetuksessa kestävä kehitys näkyy globaalin ymmärryksen laajentamisessa ja kyvyssä käsitellä kestävän kehityksen teemoja kohdekielellä. Oppilaat oppivat hankkimaan tietoa ympäristöön ja kestävyyteen liittyvistä aiheista kansainvälisistä lähteistä. Kulttuurisen moninaisuuden arvostaminen tukee sosiaalista kestävyyttä.",
          "en": "In foreign language teaching, sustainability is reflected in broadening global understanding and the ability to address sustainability themes in the target language. Pupils learn to acquire information about environmental and sustainability topics from international sources. Appreciation of cultural diversity supports social sustainability."
        }
      }
    ],
    "basicSkills": [
      {
        "code": "GF1",
        "name": {
          "local": "Suulliset taidot",
          "en": "Oral skills"
        },
        "description": {
          "local": "Suullisten taitojen kehittäminen on vieraiden kielten opetuksen ydintä. Oppilaat harjoittelevat monipuolisesti erilaisia vuorovaikutustilanteita kohdekielellä, kuten keskusteluja, mielipiteiden ilmaisua ja merkitysneuvotteluja. Opetuksessa kiinnitetään huomiota ääntämiseen, viestinnän kulttuuriseen sopivuuteen ja kommunikaation jatkamisstrategioihin.",
          "en": "Developing oral skills is at the core of foreign language teaching. Pupils practise a wide variety of interaction situations in the target language, such as conversations, expressing opinions and negotiation of meaning. Attention is paid to pronunciation, cultural appropriateness of communication and strategies for sustaining communication."
        }
      },
      {
        "code": "GF2",
        "name": {
          "local": "Kirjoittaminen",
          "en": "Writing"
        },
        "description": {
          "local": "Kirjoittamista harjoitellaan vieraiden kielten opetuksessa tuottamalla erilaisia tekstejä, kuten kertovia, kuvaavia ja vaikuttavia tekstejä kohdekielellä. Oppilaat oppivat ilmaisemaan ajatuksiaan kirjallisesti laajenevista aihepiireistä kiinnittäen huomiota keskeisiin rakenteisiin. Kirjoittaminen tukee kielitaidon kokonaisvaltaista kehittymistä.",
          "en": "Writing is practised in foreign language teaching by producing various types of texts, such as narrative, descriptive and persuasive texts in the target language. Pupils learn to express their thoughts in writing on expanding topics, paying attention to key structures. Writing supports the holistic development of language skills."
        }
      },
      {
        "code": "GF3",
        "name": {
          "local": "Lukeminen",
          "en": "Reading"
        },
        "description": {
          "local": "Lukutaitoa kehitetään vieraiden kielten opetuksessa työskentelemällä monentasoisten puhuttujen ja kirjoitettujen tekstien parissa erilaisia ymmärtämisstrategioita käyttäen. Oppilaat lukevat yleiskielisiä ja yleistajuisia tekstejä erilaisista lähteistä ja oppivat tulkitsemaan niitä. Monilukutaitoa edistetään käsittelemällä erilaisia tekstilajeja ja mediaesityksiä.",
          "en": "Reading skills are developed in foreign language teaching by working with spoken and written texts of varying levels of difficulty using different comprehension strategies. Pupils read standard and accessible texts from different sources and learn to interpret them. Multiliteracy is promoted by addressing various text types and media presentations."
        }
      },
      {
        "code": "GF4",
        "name": {
          "local": "Laskutaito",
          "en": "Numeracy"
        },
        "description": {
          "local": "Laskutaitoa käytetään vieraiden kielten opetuksessa numeeristen ilmausten, kuten lukujen, päivämäärien, kellonaikojen ja hintojen, oppimisessa ja käyttämisessä kohdekielellä. Oppilaat harjoittelevat numeerisen tiedon ymmärtämistä ja tuottamista arkielämän viestintätilanteissa vieraalla kielellä.",
          "en": "Numeracy is used in foreign language teaching for learning and using numerical expressions, such as numbers, dates, times and prices, in the target language. Pupils practise understanding and producing numerical information in everyday communication situations in the foreign language."
        }
      },
      {
        "code": "GF5",
        "name": {
          "local": "Digitaaliset taidot",
          "en": "Digital skills"
        },
        "description": {
          "local": "Digitaalisia taitoja hyödynnetään vieraiden kielten opetuksessa tieto- ja viestintäteknologian avulla viestimisessä, kohdekielisen aineiston etsimisessä verkosta ja sähköisten sanakirjojen käytössä. Oppilaat harjoittelevat vuorovaikutusta eri viestintäkanavia hyödyntäen ja oppivat arvioimaan digitaalisten lähteiden luotettavuutta.",
          "en": "Digital skills are used in foreign language teaching for communicating through information and communication technology, searching for target language material online and using electronic dictionaries. Pupils practise interaction using different communication channels and learn to evaluate the reliability of digital sources."
        }
      }
    ],
    "gradeBands": [
      {
        "afterGrade": 6,
        "label": {
          "local": "Vuosiluokat 3–6",
          "en": "Grades 3–6"
        },
        "competenceGoals": [
          {
            "code": "T1",
            "text": {
              "local": "T1 ohjata oppilasta havaitsemaan lähiympäristön ja maailman kielellinen ja kulttuurinen runsaus sekä englannin asema globaalin viestinnän kielenä",
              "en": "T1 guide the pupil to notice the linguistic and cultural richness of the immediate environment and the world, and the status of English as a language of global communication"
            },
            "coreElements": [
              "S1"
            ],
            "verbs": []
          },
          {
            "code": "T2",
            "text": {
              "local": "T2 motivoida oppilasta arvostamaan omaa kieli- ja kulttuuritaustaansa sekä maailman kielellistä ja kulttuurista moninaisuutta ja kohtaamaan ihmisiä ilman arvottavia ennakko-oletuksia",
              "en": "T2 motivate the pupil to value their own linguistic and cultural background as well as the linguistic and cultural diversity of the world, and to encounter people without prejudicial assumptions"
            },
            "coreElements": [
              "S1"
            ],
            "verbs": []
          },
          {
            "code": "T3",
            "text": {
              "local": "T3 ohjata oppilasta havaitsemaan kieliä yhdistäviä ja erottavia ilmiöitä sekä tukea oppilaan kielellisen päättelykyvyn kehittymistä",
              "en": "T3 guide the pupil to notice phenomena that connect and distinguish languages, and to support the development of the pupil's linguistic reasoning ability"
            },
            "coreElements": [
              "S1"
            ],
            "verbs": []
          },
          {
            "code": "T4",
            "text": {
              "local": "T4 ohjata oppilasta ymmärtämään, että englanniksi on saatavilla runsaasti aineistoa ja valitsemaan niistä omaa oppimistaan edistävää, sisällöltään ja vaikeustasoltaan sopivaa aineistoa",
              "en": "T4 guide the pupil to understand that a wealth of material is available in English and to select material that promotes their own learning and is suitable in content and level of difficulty"
            },
            "coreElements": [
              "S1"
            ],
            "verbs": []
          },
          {
            "code": "T5",
            "text": {
              "local": "T5 tutustua yhdessä opetuksen tavoitteisiin ja luoda salliva opiskeluilmapiiri, jossa tärkeintä on viestin välittyminen sekä kannustava yhdessä oppiminen",
              "en": "T5 explore the learning objectives together and create a permissive study atmosphere in which the most important thing is getting the message across and supportive collaborative learning"
            },
            "coreElements": [
              "S2"
            ],
            "verbs": []
          },
          {
            "code": "T6",
            "text": {
              "local": "T6 ohjata oppilasta ottamaan vastuuta omasta kielenopiskelustaan ja kannustaa harjaannuttamaan kielitaitoaan rohkeasti ja myös tieto- ja viestintäteknologiaa käyttäen sekä kokeilemaan, millaiset tavat oppia kieliä sopivat hänelle parhaiten",
              "en": "T6 guide the pupil to take responsibility for their own language learning and encourage them to practise their language skills boldly, including through the use of information and communication technology, and to try out which ways of learning languages suit them best"
            },
            "coreElements": [
              "S2"
            ],
            "verbs": []
          },
          {
            "code": "T7",
            "text": {
              "local": "T7 ohjata oppilasta harjoittelemaan vuorovaikutusta aihepiiriltään monenlaisissa tilanteissa rohkaisten viestinnän jatkumiseen mahdollisista katkoksista huolimatta",
              "en": "T7 guide the pupil to practise interaction in situations on a variety of topics, encouraging the continuation of communication despite possible breakdowns"
            },
            "coreElements": [
              "S3"
            ],
            "verbs": []
          },
          {
            "code": "T8",
            "text": {
              "local": "T8 rohkaista oppilasta pitämään yllä viestintätilannetta käyttäen monenlaisia viestinnän jatkamisen keinoja",
              "en": "T8 encourage the pupil to sustain a communicative situation using a variety of strategies for continuing communication"
            },
            "coreElements": [
              "S3"
            ],
            "verbs": []
          },
          {
            "code": "T9",
            "text": {
              "local": "T9 tukea oppilaan viestinnän kulttuurista sopivuutta tarjoamalla mahdollisuuksia harjoitella monipuolisia sosiaalisia tilanteita",
              "en": "T9 support the cultural appropriateness of the pupil's communication by providing opportunities to practise a variety of social situations"
            },
            "coreElements": [
              "S3"
            ],
            "verbs": []
          },
          {
            "code": "T10",
            "text": {
              "local": "T10 ohjata oppilasta työskentelemään vaativuudeltaan monentasoisten puhuttujen ja kirjoitettujen tekstien parissa käyttäen erilaisia ymmärtämisstrategioita",
              "en": "T10 guide the pupil to work with spoken and written texts of varying levels of difficulty using different comprehension strategies"
            },
            "coreElements": [
              "S3"
            ],
            "verbs": []
          },
          {
            "code": "T11",
            "text": {
              "local": "T11 tarjota oppilaalle mahdollisuuksia tuottaa puhetta ja kirjoitusta aihepiirejä laajentaen sekä kiinnittäen huomiota myös keskeisiin rakenteisiin ja ääntämisen perussääntöihin",
              "en": "T11 provide the pupil with opportunities to produce speech and writing while expanding the range of topics, and paying attention to key structures and basic rules of pronunciation"
            },
            "coreElements": [
              "S3"
            ],
            "verbs": []
          }
        ],
        "knowledgeCriteria": [
          {
            "gradeStep": "5",
            "label": {
              "local": "Arvosana 5 (välttävä)",
              "en": "Grade 5 (passable)"
            },
            "text": {
              "local": "Kielellisen ja kulttuurisen moninaisuuden sekä englannin kielen aseman ja merkityksen hahmottaminen: Oppilas osaa nimetä joitakin hänen lähiympäristössään tai maailmassa käytettyjä kieliä.  \n\nOppilas osaa antaa jonkin esimerkin eri englanninkielisten maiden kulttuureille tyypillisistä asioista.\nKielellinen päättely: Oppilas osaa nimetä jonkin yhtäläisyyden ja eron englannin kielen ja äidinkielensä tai muun osaamansa kielen välillä.\nEnglanninkielisen aineiston löytäminen: Oppilas osaa antaa esimerkin jostakin itselleen sopivasta englanninkielisestä aineistosta.\nEnglannin kielen opiskelun tavoitteista kertominen ja ryhmässä toimiminen: Oppilas osaa nimetä jonkin tavoitteen englannin kielen opiskelulleen.\n\nOppilas osallistuu toisinaan ryhmän toimintaan ja tekee yhteistyötä.\nVastuun ottaminen englannin kielen opiskelusta ja sopivien kielen oppimistapojen löytäminen: Oppilas ottaa ohjattuna jonkin verran vastuuta englannin kielen opiskelustaan.\n\nOppilas osaa käyttää jotakin tapaa, mukaan lukien tieto- ja viestintäteknologiaa, oppiakseen englannin kieltä ja muita kieliä.\nVuorovaikutus erilaisissa tilanteissa: Taitotaso A1.1:\n\nOppilas selviytyy satunnaisesti viestintäkumppanin tukemana muutamasta, kaikkein yleisimmin toistuvasta ja rutiininomaisesta viestintätilanteesta.\nViestintästrategioiden käyttö: Taitotaso A1.1:\n\nOppilas tarvitsee paljon apukeinoja (esim. eleet, piirtäminen, sanastot, internet).\n\nOppilas osaa joskus arvailla tai päätellä yksittäisten sanojen merkityksiä asiayhteyden, yleistiedon tai muun kielitaitonsa perusteella.\n\nOppilas osaa ilmaista, onko ymmärtänyt.\nViestinnän kulttuurinen sopivuus: Taitotaso A1.1:\n\nOppilas osaa käyttää muutamia kielelle ja kulttuurille tyypillisimpiä kohteliaisuuden ilmauksia (tervehtiminen, hyvästely, kiittäminen) joissakin kaikkein rutiininomaisimmissa sosiaalisissa kontakteissa.\nTekstien tulkintataidot: Taitotaso A1.1:\n\nOppilas ymmärtää vähäisen määrän yksittäisiä puhuttuja ja kirjoitettuja sanoja ja ilmauksia.\n \nOppilas tuntee kirjainjärjestelmän tai hyvin rajallisen määrän kirjoitusmerkkejä.\nTekstien tuottamistaidot: Taitotaso A1.1:\n\nOppilas osaa ilmaista itseään puheessa hyvin suppeasti käyttäen harjoiteltuja sanoja ja opeteltuja vakioilmaisuja.\n\nOppilas ääntää joitakin harjoiteltuja ilmauksia ymmärrettävästi ja osaa kirjoittaa joitakin erillisiä sanoja ja sanontoja.",
              "en": ""
            }
          },
          {
            "gradeStep": "7",
            "label": {
              "local": "Arvosana 7 (tyydyttävä)",
              "en": "Grade 7 (satisfactory)"
            },
            "text": {
              "local": "Kielellisen ja kulttuurisen moninaisuuden sekä englannin kielen aseman ja merkityksen hahmottaminen: Oppilas osaa kertoa, mitä kieliä hänen lähiympäristössään ja maailmassa käytetään.  \n\nOppilas osaa antaa joitakin esimerkkejä eri englanninkielisten maiden kulttuureille tyypillisistä asioista.\n\nOppilas osaa antaa esimerkin tilanteesta, jossa englantia käytetään globaalin viestinnän kielenä.\nKielellinen päättely: Oppilas osaa antaa esimerkkejä yhtäläisyyksistä ja eroista englannin kielen ja äidinkielensä tai muun osaamansa kielen välillä.\nEnglanninkielisen aineiston löytäminen: Oppilas osaa antaa esimerkkejä häntä itseään kiinnostavista englanninkielisistä aineistoista.\nEnglannin kielen opiskelun tavoitteista kertominen ja ryhmässä toimiminen: Oppilas osaa antaa joitakin esimerkkejä englannin kielen opiskelun tavoitteistaan.\n\nOppilas osallistuu ryhmän toimintaan ja tekee yhteistyötä.\nVastuun ottaminen englannin kielen opiskelusta ja sopivien kielen oppimistapojen löytäminen: Oppilas ottaa jonkin verran vastuuta englannin kielen opiskelustaan.\n\nOppilas osaa käyttää joitakin tapoja, mukaan lukien tieto- ja viestintäteknologiaa, oppiakseen englannin kieltä ja muita kieliä.\nVuorovaikutus erilaisissa tilanteissa: Taitotaso A1.3:\n\nOppilas selviytyy monista rutiininomaisista viestintätilanteista tukeutuen joskus viestintäkumppaniin.\nViestintästrategioiden käyttö: Taitotaso A1.3:\n\nOppilas osallistuu viestintään, mutta tarvitsee vielä usein apukeinoja.\n\nOppilas osaa reagoida suppein sanallisin ilmauksin, pienin elein (esim. nyökkäämällä), äännähdyksin tai muunlaisella minimipalautteella.\n\nOppilas joutuu pyytämään selvennystä tai toistoa hyvin usein.\nViestinnän kulttuurinen sopivuus: Taitotaso A1.3:\n\nOppilas osaa käyttää yleisimpiä kohteliaaseen kielenkäyttöön kuuluvia ilmauksia monissa rutiininomaisissa sosiaalisissa kontakteissa.\nTekstien tulkintataidot: Taitotaso A1.3:\n\nOppilas ymmärtää yksinkertaista, tuttua sanastoa ja ilmaisuja sisältävää kirjoitettua tekstiä ja hidasta puhetta asiayhteyden tukemana.\n\nOppilas pystyy löytämään tarvitsemansa yksinkertaisen tiedon lyhyestä tekstistä.\nTekstien tuottamistaidot: Taitotaso A1.3:\n\nOppilas osaa rajallisen määrän lyhyitä, ulkoa opeteltuja ilmauksia, keskeistä sanastoa ja perustason lauserakenteita.\n\nOppilas pystyy kertomaan arkisista ja itselleen tärkeistä asioista käyttäen suppeaa ilmaisuvarastoa ja kirjoittamaan yksinkertaisia viestejä.\n\nOppilas ääntää harjoitellut ilmaisut ymmärrettävästi.",
              "en": ""
            }
          },
          {
            "gradeStep": "8",
            "label": {
              "local": "Arvosana 8 (hyvä)",
              "en": "Grade 8 (good)"
            },
            "text": {
              "local": "Kielellisen ja kulttuurisen moninaisuuden sekä englannin kielen aseman ja merkityksen hahmottaminen: Oppilas osaa kertoa lähiympäristönsä ja maailman kielellisestä runsaudesta.\n\nOppilas osaa antaa esimerkkejä eri englanninkielisten maiden kulttuureille tyypillisistä asioista.\n\nOppilas osaa kertoa, missä ja millaisissa tilanteissa englantia käytetään globaalin viestinnän kielenä.\nKielellinen päättely: Oppilas osaa kertoa yhtäläisyyksistä ja eroista englannin kielen ja äidinkielensä tai muun osaamansa \nkielen välillä.\n\nOppilas osaa nimetä joitakin kielellistä päättelyä tukevia strategioita.\nEnglanninkielisen aineiston löytäminen: Oppilas osaa kertoa englanninkielisistä aineistoista, jotka ovat hänelle itselleen sopivia ja jotka kiinnostavat häntä.\nEnglannin kielen opiskelun tavoitteista kertominen ja ryhmässä toimiminen: Oppilas osaa kertoa englannin kielen opiskelun tavoitteistaan.\n\nOppilas osallistuu ryhmän toimintaan ja tekee yhteistyötä kannustavasti.\nVastuun ottaminen englannin kielen opiskelusta ja sopivien kielen oppimistapojen löytäminen: Oppilas ottaa melko paljon vastuuta englannin kielen opiskelustaan.\n\nOppilas osaa käyttää useita oppimistaan edistäviä tapoja, mukaan lukien tieto- ja viestintäteknologiaa, oppiakseen englannin kieltä ja muita kieliä.\nVuorovaikutus erilaisissa tilanteissa: Taitotaso A2.1:\n\nOppilas pystyy vaihtamaan ajatuksia tai tietoja tutuissa ja jokapäiväisissä tilanteissa sekä toisinaan ylläpitämään viestintätilannetta.\nViestintästrategioiden käyttö: Taitotaso A2.1:\n\nOppilas osallistuu enenevässä määrin viestintään. \n\nOppilas turvautuu harvemmin ei-kielellisiin ilmaisuihin. \n\nOppilas joutuu pyytämään toistoa tai selvennystä melko usein.\n\nOppilas osaa jonkin verran soveltaa viestintäkumppanin ilmaisuja omassa viestinnässään.\nViestinnän kulttuurinen sopivuus: Taitotaso A2.1:\n\nOppilas selviytyy lyhyistä sosiaalisista tilanteista.\n\nOppilas osaa käyttää yleisimpiä kohteliaita tervehdyksiä ja puhuttelumuotoja sekä esittää kohteliaasti esimerkiksi pyyntöjä, kutsuja, ehdotuksia ja anteeksipyyntöjä ja vastata sellaisiin.\nTekstien tulkintataidot: Taitotaso A2.1:\n\nOppilas ymmärtää helppoja, tuttua sanastoa ja ilmaisuja sekä selkeää puhetta sisältäviä tekstejä. \n\nOppilas ymmärtää lyhyiden, yksinkertaisten, itseään kiinnostavien viestien ydinsisällön ja tekstin pääajatukset tuttua sanastoa sisältävästä, ennakoitavasta tekstistä.\n\nOppilas pystyy hyvin yksinkertaiseen päättelyyn asiayhteyden tukemana.\nTekstien tuottamistaidot: Taitotaso A2.1:\n\nOppilas pystyy kertomaan jokapäiväisistä ja konkreettisista sekä itselleen tärkeistä asioista käyttäen yksinkertaisia lauseita ja konkreettista sanastoa.\n \nOppilas osaa helposti ennakoitavan perussanaston ja monia keskeisimpiä rakenteita.\n\nOppilas osaa soveltaa joitakin ääntämisen perussääntöjä muissakin kuin harjoitelluissa ilmauksissa.",
              "en": ""
            }
          },
          {
            "gradeStep": "9",
            "label": {
              "local": "Arvosana 9 (kiitettävä)",
              "en": "Grade 9 (excellent)"
            },
            "text": {
              "local": "Kielellisen ja kulttuurisen moninaisuuden sekä englannin kielen aseman ja merkityksen hahmottaminen: Oppilas osaa kertoa monipuolisesti lähiympäristönsä ja maailman kielellistä runsautta.\n\nOppilas osaa vertailla eri englanninkielisten maiden kulttuureille tyypillisiä asioita.\n\nOppilas osaa kertoa, missä ja millaisissa tilanteissa sekä miksi englantia käytetään globaalin viestinnän kielenä.\nKielellinen päättely: Oppilas osaa vertailla yhtäläisyyksiä ja eroja englannin kielen ja äidinkielensä tai muun osaamansa kielen välillä. \n\nOppilas osaa käyttää sopivia kielellistä päättelyä tukevia strategioita.\nEnglanninkielisen aineiston löytäminen: Oppilas osaa vertailla englanninkielisiä aineistoja, jotka ovat hänelle itselleen sopivia ja jotka kiinnostavat häntä.\nEnglannin kielen opiskelun tavoitteista kertominen ja ryhmässä toimiminen: Oppilas osaa kertoa englannin kielen opiskelun tavoitteistaan ja kertoa, kuinka hän työskentelee saavuttaakseen tavoitteensa.\n\nOppilas osallistuu ryhmän toimintaan ja tekee yhteistyötä monipuolisesti ja kannustavasti.\nVastuun ottaminen englannin kielen opiskelusta ja sopivien kielen oppimistapojen löytäminen: Oppilas ottaa paljon vastuuta englannin kielen opiskelustaan.\n\nOppilas osaa käyttää monipuolisesti oppimistaan edistäviä tapoja, mukaan lukien tieto- ja viestintäteknologiaa oppiakseen englannin kieltä ja muita kieliä.\nVuorovaikutus erilaisissa tilanteissa: Taitotaso A2.2:\n\nOppilas selviää kohtalaisesti monenlaisista jokapäiväisistä viestintätilanteista.\n\nOppilas pystyy enenevässä määrin olemaan aloitteellinen viestintätilanteessa.\nViestintästrategioiden käyttö: Taitotaso A2.2:\n\nOppilas osallistuu enenevässä määrin viestintään käyttäen tarvittaessa vakiosanontoja pyytäessään tarkennusta avainsanoista.\n \nOppilas joutuu pyytämään toistoa tai selvennystä silloin tällöin ja käyttää esim. lähikäsitettä tai yleisempää käsitettä, kun ei tiedä täsmällistä käsitettä (koira/eläin tai talo/mökki).\nViestinnän kulttuurinen sopivuus: Taitotaso A2.2:\n\nOppilas osaa käyttää kieltä yksinkertaisella tavalla kaikkein keskeisimpiin tarkoituksiin, kuten tiedonvaihtoon sekä mielipiteiden ja asenteiden asianmukaiseen ilmaisemiseen.\n\nOppilas pystyy keskustelemaan kohteliaasti käyttäen tavanomaisia ilmauksia ja perustason viestintärutiineja.\nTekstien tulkintataidot: Taitotaso A2.2:\n\nOppilas pystyy seuraamaan hyvin summittaisesti selväpiirteisen asiapuheen pääkohtia, tunnistaa usein ympärillään käytävän keskustelun aiheen ja ymmärtää pääasiat tuttua sanastoa sisältävästä yleiskielisestä tekstistä tai hitaasta puheesta.\n\nOppilas osaa päätellä tuntemattomien sanojen merkityksiä asiayhteydestä.\nTekstien tuottamistaidot: Taitotaso A2.2:\n\nOppilas osaa kuvata luettelomaisesti (ikäkaudelleen tyypillisiä) jokapäiväiseen elämään liittyviä asioita käyttäen tavallista sanastoa ja joitakin idiomaattisia ilmauksia sekä perustason rakenteita ja joskus hiukan vaativampiakin.\n\nOppilas osaa soveltaa joitakin ääntämisen perussääntöjä muissakin kuin harjoitelluissa ilmauksissa.",
              "en": ""
            }
          }
        ]
      },
      {
        "afterGrade": 9,
        "label": {
          "local": "Vuosiluokat 7–9",
          "en": "Grades 7–9"
        },
        "competenceGoals": [
          {
            "code": "T1",
            "text": {
              "local": "T1 edistää oppilaan taitoa pohtia englannin asemaan ja variantteihin liittyviä ilmiöitä ja arvoja antaa oppilaalle valmiuksia kehittää kulttuurienvälistä toimintakykyä",
              "en": "T1 promote the pupil's ability to reflect on phenomena and values related to the status and varieties of English, and provide the pupil with the capacity to develop intercultural competence"
            },
            "coreElements": [
              "S1"
            ],
            "verbs": []
          },
          {
            "code": "T2",
            "text": {
              "local": "T2 kannustaa löytämään kiinnostavia englanninkielisiä sisältöjä ja toimintaympäristöjä, jotka laajentavat käsitystä globalisoituvasta maailmasta ja siinä toimimisen mahdollisuuksista",
              "en": "T2 encourage the pupil to find interesting English-language content and environments that broaden their understanding of the globalising world and the possibilities of operating within it"
            },
            "coreElements": [
              "S1"
            ],
            "verbs": []
          },
          {
            "code": "T3",
            "text": {
              "local": "T3 ohjata oppilasta havaitsemaan, millaisia säännönmukaisuuksia englannin kielessä on, miten samoja asioita ilmaistaan muissa kielissä sekä käyttämään kielitiedon käsitteitä oppimisensa tukena",
              "en": "T3 guide the pupil to notice what kinds of regularities exist in English, how the same things are expressed in other languages, and to use linguistic concepts to support their learning"
            },
            "coreElements": [
              "S1"
            ],
            "verbs": []
          },
          {
            "code": "T4",
            "text": {
              "local": "T4 rohkaista oppilasta asettamaan tavoitteita, hyödyntämään monipuolisia tapoja oppia englantia ja arvioimaan oppimistaan itsenäisesti ja yhteistyössä sekä ohjata oppilasta myönteiseen vuorovaikutukseen, jossa tärkeintä on viestin välittyminen",
              "en": "T4 encourage the pupil to set goals, to use diverse ways of learning English, and to evaluate their learning independently and collaboratively, and to guide the pupil towards positive interaction in which the most important thing is getting the message across"
            },
            "coreElements": [
              "S2"
            ],
            "verbs": []
          },
          {
            "code": "T5",
            "text": {
              "local": "T5 kehittää oppilaan itsenäisyyttä soveltaa luovasti kielitaitoaan sekä jatkuvan kieltenopiskelun valmiuksia",
              "en": "T5 develop the pupil's independence in applying their language skills creatively and their readiness for lifelong language learning"
            },
            "coreElements": [
              "S2"
            ],
            "verbs": []
          },
          {
            "code": "T6",
            "text": {
              "local": "T6 rohkaista oppilasta osallistumaan keskusteluihin monenlaisista oppilaiden ikätasolle ja elämänkokemukseen sopivista aiheista, joissa käsitellään myös mielipiteitä",
              "en": "T6 encourage the pupil to participate in conversations on a variety of topics appropriate to the pupils' age level and life experience, including topics that involve opinions"
            },
            "coreElements": [
              "S3"
            ],
            "verbs": []
          },
          {
            "code": "T7",
            "text": {
              "local": "T7 tukea oppilaan aloitteellisuutta viestinnässä, kompensaatiokeinojen käytössä ja merkitysneuvottelun käymisessä",
              "en": "T7 support the pupil's initiative in communication, in the use of compensation strategies, and in negotiation of meaning"
            },
            "coreElements": [
              "S3"
            ],
            "verbs": []
          },
          {
            "code": "T8",
            "text": {
              "local": "T8 auttaa oppilasta tunnistamaan viestinnän kulttuurisia piirteitä ja tukea oppilaiden rakentavaa kulttuurienvälistä viestintää",
              "en": "T8 help the pupil to recognise cultural features of communication and to support pupils' constructive intercultural communication"
            },
            "coreElements": [
              "S3"
            ],
            "verbs": []
          },
          {
            "code": "T9",
            "text": {
              "local": "T9 tarjota oppilaalle mahdollisuuksia kuulla ja lukea monenlaisia itselleen merkityksellisiä yleiskielisiä ja yleistajuisia tekstejä erilaisista lähteistä sekä tulkita niitä käyttäen erilaisia strategioita",
              "en": "T9 provide the pupil with opportunities to listen to and read various types of personally meaningful standard and accessible texts from different sources, and to interpret them using different strategies"
            },
            "coreElements": [
              "S3"
            ],
            "verbs": []
          },
          {
            "code": "T10",
            "text": {
              "local": "T10 ohjata oppilasta tuottamaan sekä puhuttua että kirjoitettua tekstiä erilaisiin tarkoituksiin yleisistä ja itselleen merkityksellisistä aiheista kiinnittäen huomiota rakenteiden monipuolisuuteen ja ohjaten hyvään ääntämiseen",
              "en": "T10 guide the pupil to produce both spoken and written text for various purposes on general and personally meaningful topics, paying attention to the versatility of structures and guiding good pronunciation"
            },
            "coreElements": [
              "S3"
            ],
            "verbs": []
          }
        ],
        "knowledgeCriteria": [
          {
            "gradeStep": "5",
            "label": {
              "local": "Arvosana 5 (välttävä)",
              "en": "Grade 5 (passable)"
            },
            "text": {
              "local": "Kielen asemaan ja variantteihin liittyvien kysymysten huomaaminen ja kulttuurien välinen toimintakyky: Oppilas osaa nimetä joitakin maita, joissa englantia puhutaan.\n\nOppilas osaa kertoa jotakin kielialueen maiden kulttuureista ja elämänmuodoista.\nMaailmankansalaisen taitojen kehittäminen englannin kieltä hyödyntämällä: Oppilas osaa antaa esimerkkejä joistakin aineistoista ja toimintaympäristöistä, joissa voi käyttää englannin kieltä.\nKielellinen päättely: Oppilas osaa tehdä havaintoja joistakin englannin kielen säännönmukaisuuksista.\nTavoitteiden asettaminen, opiskelustrategioiden hyödyntäminen, oppimisen reflektointi ja vuorovaikutuksessa toimimisen tapojen hahmottaminen: Oppilas osaa käyttää joitakin itselle sopivia kielenoppimistapoja.\n\nOppilas osaa antaa joitakin esimerkkejä tavoista toimia rakentavasti vuorovaikutuksessa.\nJatkuvan kielenopiskelun valmiuksien kehittyminen: Oppilas osaa antaa joitakin esimerkkejä mahdollisuuksista kehittää englannin kielen taitoaan.\nVuorovaikutus erilaisissa tilanteissa: Taitotaso A1.3 \nOppilas selviytyy monista rutiininomaisista viestintätilanteista tukeutuen joskus viestintäkumppaniin.\nViestintästrategioiden käyttö: Taitotaso A1.3 Oppilas osallistuu viestintään, mutta tarvitsee edelleen usein apukeinoja.\n \nOppilas osaa reagoida suppein\nsanallisin ilmauksin, pienin elein (esim. nyökkäämällä), äännähdyksin tai muunlaisella minimipalautteella.\n\nOppilas joutuu pyytämään selvennystä tai toistoa hyvin\nusein.\nViestinnän kulttuurinen sopivuus: Taitotaso A1.3 Oppilas osaa käyttää yleisimpiä kohteliaaseen\nkielenkäyttöön kuuluvia ilmauksia monissa rutiininomaisissa sosiaalisissa kontakteissa.\nTekstien tulkintataidot: Taitotaso A1.3 Oppilas ymmärtää yksinkertaista, tuttua\nsanastoa ja ilmaisuja sisältävää kirjoitettua tekstiä ja hidasta puhetta asiayhteyden tukemana.\n\nOppilas pystyy löytämään tarvitsemansa yksinkertaisen tiedon lyhyestä tekstistä.\nTekstien tuottamistaidot: Taitotaso A1.3\nOppilas osaa rajallisen\nmäärän lyhyitä, ulkoa opeteltuja ilmauksia, keskeistä sanastoa ja\nperustason lauserakenteita.\n\nOppilas pystyy kertomaan arkisista ja itselleen tärkeistä asioista käyttäen suppeaa ilmaisuvarastoa ja kirjoittamaan yksinkertaisia viestejä sekä ääntää harjoitellut ilmaisut ymmärrettävästi.",
              "en": ""
            }
          },
          {
            "gradeStep": "7",
            "label": {
              "local": "Arvosana 7 (tyydyttävä)",
              "en": "Grade 7 (satisfactory)"
            },
            "text": {
              "local": "Kielen asemaan ja variantteihin liittyvien kysymysten huomaaminen ja kulttuurien välinen toimintakyky: Oppilas osaa kertoa, missä englantia puhutaan ja että sitä puhutaan eri tavoin.\n\nOppilas osaa kuvailla kielialueen maiden kulttuureja ja elämänmuotoja. \n     \nOppilas osaa nimetä vuorovaikutukseen liittyviä kulttuurisia piirteitä.\nMaailmankansalaisen taitojen kehittäminen englannin kieltä hyödyntämällä: Oppilas osaa nimetä englanninkielisiä aineistoja ja toimintaympäristöjä, jotka edistävät hänen oppimistaan.\nKielellinen päättely: Oppilas osaa tehdä joitakin johtopäätöksiä englannin kielen säännönmukaisuuksista.\n\nOppilas osaa antaa joitakin esimerkkejä siitä, miten sama asia ilmaistaan englannissa ja jossakin muussa kielessä.\n\nOppilas osaa antaa joitakin esimerkkejä englannin kielen kielitiedon käsitteistä ja osaa käyttää niitä kielitaitonsa kehittämiseen.\nTavoitteiden asettaminen, opiskelustrategioiden hyödyntäminen, oppimisen reflektointi ja vuorovaikutuksessa toimimisen tapojen hahmottaminen: Oppilas osaa käyttää yleisimpiä itselle sopivia kielenoppimistapoja.\n\nOppilas osaa kuvata joitakin tapoja toimia rakentavasti vuorovaikutuksessa.\nJatkuvan kielenopiskelun valmiuksien kehittyminen: Oppilas osaa kuvailla mahdollisuuksia kehittää englannin kielen taitoaan myös koulun päätyttyä.\nVuorovaikutus erilaisissa tilanteissa: Taitotaso A2.2\nOppilas selviää kohtalaisesti monenlaisista jokapäiväisistä viestintätilanteista ja pystyy enenevässä määrin olemaan aloitteellinen viestintätilanteessa.\nViestintästrategioiden käyttö: Taitotaso A2.2 Oppilas osallistuu enenevässä määrin viestintään käyttäen tarvittaessa vakiosanontoja pyytäessään tarkennusta avainsanoista. \n\nOppilas joutuu pyytämään toistoa tai selvennystä silloin tällöin.\n\nOppilas käyttää esim. lähikäsitettä tai yleisempää käsitettä, kun ei tiedä täsmällistä (koira/eläin tai talo/mökki).\nViestinnän kulttuurinen sopivuus: Taitotaso A2.2 Oppilas osaa käyttää kieltä yksinkertaisella tavalla kaikkein keskeisimpiin tarkoituksiin, kuten tiedonvaihtoon sekä mielipiteiden ja asenteiden asianmukaiseen ilmaisemiseen. \n\nOppilas pystyy\nkeskustelemaan kohteliaasti käyttäen tavanomaisia ilmauksia ja perustason viestintärutiineja.\nTekstien tulkintataidot: Taitotaso A2.2\nOppilas pystyy seuraamaan\nhyvin summittaisesti selväpiirteisen asiapuheen pääkohtia, tunnistaa usein ympärillään käytävän keskustelun aiheen sekä ymmärtää pääasiat tuttua sanastoa sisältävästä yleiskielisestä tekstistä tai hitaasta puheesta.\n\nOppilas osaa päätellä tuntemattomien sanojen merkityksiä asiayhteydestä.\nTekstien tuottamistaidot: Taitotaso A2.2\nOppilas osaa kuvata luettelomaisesti (ikäkaudelleen tyypillisiä) jokapäiväiseen elämään liittyviä asioita käyttäen tavallista sanastoa ja joitakin idiomaattisia ilmauksia sekä perustason rakenteita ja joskus hiukan vaativampiakin.\n\nOppilas osaa soveltaa joitakin ääntämisen perussääntöjä muissakin kuin harjoitelluissa ilmauksissa.",
              "en": ""
            }
          },
          {
            "gradeStep": "8",
            "label": {
              "local": "Arvosana 8 (hyvä)",
              "en": "Grade 8 (good)"
            },
            "text": {
              "local": "Kielen asemaan ja variantteihin liittyvien kysymysten huomaaminen ja kulttuurien välinen toimintakyky: Oppilas osaa kertoa englannin asemasta maailmankielenä.\n \nOppilas osaa vertailla kielialueen maiden kulttuureja ja elämänmuotoja.\n\nOppilas osaa kertoa kulttuurisista piirteistä vuorovaikutuksessa.\nMaailmankansalaisen taitojen kehittäminen englannin kieltä hyödyntämällä: Oppilas osaa vertailla englanninkielisiä aineistoja ja toimintaympäristöjä, jotka edistävät hänen oppimistaan\nKielellinen päättely: Oppilas osaa tehdä johtopäätöksiä englannin kielen säännönmukaisuuksista.\n\nOppilas osaa kertoa, miten sama asia ilmaistaan englannissa ja jossakin muussa kielessä.\n\nOppilas osaa kertoa kohdekielen keskeisistä kielitiedon käsitteistä ja käyttää niitä kielitaitonsa kehittämiseen.\nTavoitteiden asettaminen, opiskelustrategioiden hyödyntäminen, oppimisen reflektointi ja vuorovaikutuksessa toimimisen tapojen hahmottaminen: Oppilas osaa käyttää keskeisimpiä itselle sopivia kielenoppimistapoja.\n  \nOppilas osaa vertailla tapoja toimia rakentavasti vuorovaikutuksessa.\nJatkuvan kielenopiskelun valmiuksien kehittyminen: Oppilas osaa vertailla erilaisia mahdollisuuksia soveltaa ja kehittää englannin kielen taitoaan myös koulun päätyttyä.\nVuorovaikutus erilaisissa tilanteissa: Taitotaso B1.1 Oppilas pystyy viestimään, osallistumaan keskusteluihin ja ilmaisemaan mielipiteitään melko vaivattomasti jokapäiväisissä viestintätilanteissa.\nViestintästrategioiden käyttö: Taitotaso B1.1 Oppilas pystyy jossain määrin olemaan aloitteellinen viestinnän eri vaiheissa ja osaa varmistaa, onko viestintäkumppani ymmärtänyt viestin sekä kiertää tai korvata tuntemattoman sanan tai muotoilla viestinsä uudelleen. Oppilas pystyy neuvottelemaan tuntemattomien ilmauksien merkityksistä.\nViestinnän kulttuurinen sopivuus: Taitotaso B1.1 Oppilas osoittaa tuntevansa tärkeimmät kohteliaisuussäännöt. Oppilas pystyy ottamaan vuorovaikutuksessaan huomioon joitakin tärkeimpiä kulttuurisiin käytänteisiin liittyviä näkökohtia.\nTekstien tulkintataidot: Taitotaso B1.1 Oppilas ymmärtää pääasiat ja joitakin yksityiskohtia selkeästä ja lähes normaalitempoisesta yleiskielisestä puheesta tai yleistajuisesta kirjoitetusta tekstistä ja ymmärtää yhteiseen kokemukseen tai yleistietoon perustuvaa puhetta tai kirjoitettua tekstiä. Oppilas löytää pääajatukset, avainsanat ja tärkeitä yksityiskohtia myös valmistautumatta.\nTekstien tuottamistaidot: Taitotaso B1.1 Oppilas osaa kertoa ydinkohdat ja myös hiukan yksityiskohtia erilaisista jokapäiväiseen elämään liittyvistä itseään kiinnostavista todellisista tai kuvitteellisista aiheista käyttäen melko laajaa sanastoa ja rakennevalikoimaa sekä joitakin yleisiä fraaseja ja idiomeja. Oppilas osaa soveltaa useita ääntämisen perussääntöjä muissakin kuin harjoitelluissa ilmauksissa.",
              "en": ""
            }
          },
          {
            "gradeStep": "9",
            "label": {
              "local": "Arvosana 9 (kiitettävä)",
              "en": "Grade 9 (excellent)"
            },
            "text": {
              "local": "Kielen asemaan ja variantteihin liittyvien kysymysten huomaaminen ja kulttuurien välinen toimintakyky: Oppilas osaa pohtia englannin asemaa maailmankielenä ja siihen liittyviä ilmiöitä.\n\nOppilas osaa vertailla ja pohtia kielialueen maiden kulttuureja ja elämänmuotoja.\n\nOppilas osaa vertailla ja pohtia kulttuurisia piirteitä vuorovaikutuksessa.\nMaailmankansalaisen taitojen kehittäminen englannin kieltä hyödyntämällä: Oppilas osaa pohtia, miten hän voi hyödyntää englanninkielisiä aineistoja ja toimintaympäristöjä omaa oppimistaan edistääkseen.\nKielellinen päättely: Oppilas osaa tehdä johtopäätöksiä englannin kielen säännönmukaisuuksista ja soveltaa niitä.\n\nOppilas osaa vertailla, miten sama asia ilmaistaan englannissa ja jossakin muussa kielessä.\n\nOppilas tuntee englannin kielen keskeisiä kielitiedon käsitteitä ja osaa käyttää niitä\nkielitaitonsa kehittämiseen.\nTavoitteiden asettaminen, opiskelustrategioiden hyödyntäminen, oppimisen reflektointi ja vuorovaikutuksessa toimimisen tapojen hahmottaminen: Oppilas osaa käyttää monipuolisia itselle sopivia tapoja oppia englannin kieltä.\n\nOppilas osaa vertailla ja pohtia tapoja toimia rakentavasti vuorovaikutuksessa.\nJatkuvan kielenopiskelun valmiuksien kehittyminen: Oppilas osaa pohtia ja vertailla erilaisia mahdollisuuksia soveltaa ja kehittää englannin kielen taitoaan myös koulun päätyttyä.\nVuorovaikutus erilaisissa tilanteissa: Taitotaso B1.1/B1.2\nOppilas pystyy viestimään, osallistumaan\nkeskusteluihin ja ilmaisemaan\nmielipiteitään myös joissakin vaativammissa tilanteissa, kuten keskusteltaessa ajankohtaisesta tapahtumasta.\nViestintästrategioiden käyttö: Taitotaso B1.1/B1.2 Oppilas pystyy olemaan aloitteellinen tuttua aihetta käsittelevässä vuorovaikutustilanteessa ja osaa varmistaa, onko viestintäkumppani ymmärtänyt viestin, korjata väärinymmärryksiä sekä kiertää tai korvata tuntemattoman sanan tai muotoilla viestinsä uudelleen. \n\nOppilas pystyy neuvottelemaan tuntemattomien ja melko mutkikkaidenkin ilmauksien merkityksistä.\nViestinnän kulttuurinen sopivuus: Taitotaso B1.1/B1.2 Oppilas osoittaa tuntevansa tärkeimmät kohteliaisuussäännöt ja osaa kiinnittää huomiota kielenkäytön muodollisuuteen. \n\nOppilas pystyy ottamaan vuorovaikutuksessaan huomioon tärkeimpiä kulttuurisia käytänteitä.\nTekstien tulkintataidot: Taitotaso B1.1/B1.2\nOppilas ymmärtää pääasiat ja useita yksityiskohtia hieman vaativammasta normaalitempoisesta yleiskielisestä puheesta tai yleistajuisesta kirjoitetusta tekstistä.\n\nOppilas ymmärtää yhteiseen kokemukseen tai yleistietoon perustuvaa puhetta tai kirjoitettua tekstiä.\n\nOppilas löytää pääajatukset, avainsanat ja tärkeitä yksityiskohtia myös valmistautumatta.\nTekstien tuottamistaidot: Taitotaso B1.1/B1.2\nOppilas osaa kertoa ydinkohdat ja useita yksityiskohtia erilaisista jokapäiväiseen elämään liittyvistä itseään kiinnostavista todellisista tai kuvitteellisista aiheista käyttäen melko laajaa sanastoa ja rakennevalikoimaa sekä yleisiä fraaseja ja idiomeja.\n\nOppilas osaa soveltaa useita ääntämisen perussääntöjä muissakin kuin harjoitelluissa ilmauksissa.",
              "en": ""
            }
          }
        ]
      }
    ]
  }
}